datetime_zones/__init__.py
datetime_zones-2.3.9.dist-info/METADATA
datetime_zones-2.3.9.dist-info/WHEEL
datetime_zones-2.3.9.dist-info/top_level.txt
datetime_zones-2.3.9.dist-info/RECORD
