Metadata-Version: 2.1
Name: datetime-zones
Version: 2.3.9
Summary: Datetime zones package
Author-email: Xavier Oleko <oleko@xavier.com>
Classifier: Programming Language :: Python :: 3
Classifier: License :: OSI Approved :: MIT License
Classifier: Operating System :: OS Independent
Requires-Python: >=3.7
